meraki_dashboard_exporter/__init__.py
meraki_dashboard_exporter/__main__.py
meraki_dashboard_exporter/__version__.py
meraki_dashboard_exporter/app.py
meraki_dashboard_exporter/py.typed
meraki_dashboard_exporter/api/__init__.py
meraki_dashboard_exporter/api/client.py
meraki_dashboard_exporter/collectors/__init__.py
meraki_dashboard_exporter/collectors/alerts.py
meraki_dashboard_exporter/collectors/clients.py
meraki_dashboard_exporter/collectors/config.py
meraki_dashboard_exporter/collectors/device.py
meraki_dashboard_exporter/collectors/manager.py
meraki_dashboard_exporter/collectors/mt_sensor.py
meraki_dashboard_exporter/collectors/network_health.py
meraki_dashboard_exporter/collectors/organization.py
meraki_dashboard_exporter/collectors/devices/__init__.py
meraki_dashboard_exporter/collectors/devices/base.py
meraki_dashboard_exporter/collectors/devices/mg.py
meraki_dashboard_exporter/collectors/devices/mr.py
meraki_dashboard_exporter/collectors/devices/ms.py
meraki_dashboard_exporter/collectors/devices/mt.py
meraki_dashboard_exporter/collectors/devices/mv.py
meraki_dashboard_exporter/collectors/devices/mx.py
meraki_dashboard_exporter/collectors/network_health_collectors/__init__.py
meraki_dashboard_exporter/collectors/network_health_collectors/base.py
meraki_dashboard_exporter/collectors/network_health_collectors/bluetooth.py
meraki_dashboard_exporter/collectors/network_health_collectors/connection_stats.py
meraki_dashboard_exporter/collectors/network_health_collectors/data_rates.py
meraki_dashboard_exporter/collectors/network_health_collectors/rf_health.py
meraki_dashboard_exporter/collectors/organization_collectors/__init__.py
meraki_dashboard_exporter/collectors/organization_collectors/api_usage.py
meraki_dashboard_exporter/collectors/organization_collectors/base.py
meraki_dashboard_exporter/collectors/organization_collectors/client_overview.py
meraki_dashboard_exporter/collectors/organization_collectors/license.py
meraki_dashboard_exporter/core/__init__.py
meraki_dashboard_exporter-0.26.0.dist-info/licenses/LICENSE
meraki_dashboard_exporter-0.26.0.dist-info/METADATA
meraki_dashboard_exporter-0.26.0.dist-info/WHEEL
meraki_dashboard_exporter-0.26.0.dist-info/top_level.txt
meraki_dashboard_exporter-0.26.0.dist-info/RECORD
