Metadata-Version: 2.4
Name: meraki-dashboard-exporter
Version: 0.26.0
Summary: Prometheus exporter for Cisco Meraki Dashboard API metrics
Author-email: Rob Knight <12484127+rknightion@users.noreply.github.com>
License: Apache-2.0
Keywords: cisco,iot,meraki,sensors
Classifier: Programming Language :: Python :: 3 :: Only
Classifier: Programming Language :: Python :: 3.13
Requires-Python: >=3.13
License-File: LICENSE
Requires-Dist: anyio>=4.6
Requires-Dist: cryptography>=45.0.5
Requires-Dist: fastapi>=0.115
Requires-Dist: httpx>=0.27
Requires-Dist: jinja2>=3.1
Requires-Dist: meraki>=2.0.3
Requires-Dist: opentelemetry-api>=1.29
Requires-Dist: opentelemetry-exporter-otlp>=1.29
Requires-Dist: opentelemetry-instrumentation-fastapi>=0.50b0
Requires-Dist: opentelemetry-instrumentation-httpx>=0.50b0
Requires-Dist: opentelemetry-instrumentation-logging>=0.50b0
Requires-Dist: opentelemetry-instrumentation-requests>=0.50b0
Requires-Dist: opentelemetry-instrumentation-threading>=0.50b0
Requires-Dist: opentelemetry-sdk>=1.29
Requires-Dist: prometheus-client>=0.22.1
Requires-Dist: psutil>=5.9
Requires-Dist: pydantic>=2.10
Requires-Dist: pydantic-settings>=2.6
Requires-Dist: safety>=3.2.9
Requires-Dist: structlog>=24.4
Requires-Dist: uvicorn[standard]>=0.32
Dynamic: license-file
